say_namaste.py
say_namaste-0.0.2.dist-info/LICENSE.txt
say_namaste-0.0.2.dist-info/METADATA
say_namaste-0.0.2.dist-info/WHEEL
say_namaste-0.0.2.dist-info/top_level.txt
say_namaste-0.0.2.dist-info/RECORD
